pyroll/misaka_flow_stress.py
pyroll_misaka_flow_stress-3.0.0.dist-info/METADATA
pyroll_misaka_flow_stress-3.0.0.dist-info/WHEEL
pyroll_misaka_flow_stress-3.0.0.dist-info/licenses/LICENSE
pyroll_misaka_flow_stress-3.0.0.dist-info/RECORD
