Metadata-Version: 2.3
Name: pyroll-misaka-flow-stress
Version: 3.0.0
Summary: Plugin for PyRolL providing the constitutive flow stress function from Y. Misaka.
Project-URL: Homepage, https://pyroll-project.github.io
Project-URL: Repository, https://github.com/pyroll-project/pyroll-misaka-flow-stress
Project-URL: Documentation, https://github.com/pyroll-project/pyroll-misaka-flow-stress/blob/main/docs/docs.pdf
Author-email: Christoph Renzing <christoph.renzing@imf.tu-freiberg.de>
License-Expression: BSD-3-Clause
License-File: LICENSE
Classifier: Intended Audience :: Manufacturing
Classifier: Intended Audience :: Science/Research
Classifier: Operating System :: OS Independent
Classifier: Topic :: Scientific/Engineering
Requires-Python: <4.0,>=3.9
Requires-Dist: pyroll-core~=3.0
